MANIFEST.in
README.txt
setup.cfg
setup.py
collective/__init__.py
collective.dnifield.egg-info/PKG-INFO
collective.dnifield.egg-info/SOURCES.txt
collective.dnifield.egg-info/dependency_links.txt
collective.dnifield.egg-info/entry_points.txt
collective.dnifield.egg-info/namespace_packages.txt
collective.dnifield.egg-info/not-zip-safe
collective.dnifield.egg-info/paster_plugins.txt
collective.dnifield.egg-info/requires.txt
collective.dnifield.egg-info/top_level.txt
collective/dnifield/__init__.py
collective/dnifield/field.py
collective/dnifield/tests.py
docs/HISTORY.txt
docs/INSTALL.txt
docs/LICENSE.txt