Metadata-Version: 1.0
Name: collective.dnifield
Version: 1.0a1
Summary: A field to enter a national identity number.
Home-page: http://svn.plone.org/svn/collective/collective.dnifield
Author: Israel Saeta Pérez
Author-email: israel.saeta@dukebody.com
License: GPL
Keywords: dni nif field
Platform: UNKNOWN
Classifier: Development Status :: 3 - Alpha
Classifier: Framework :: Zope3
Classifier: Programming Language :: Python
Classifier: License :: OSI Approved :: GNU General Public License (GPL)
